<annotation>
	<folder>images</folder>
	<filename>129.jpg</filename>
	<path>C:/Users/pol20/Desktop/Nike DataSet/images/129.jpg</path>
	<source>
		<database>Unknown</database>
	</source>
	<size>
		<width>276</width>
		<height>183</height>
		<depth>3</depth>
	</size>
	<segmented>0</segmented>
	<object>
		<name>nike</name>
		<pose>Unspecified</pose>
		<truncated>0</truncated>
		<difficult>0</difficult>
		<bndbox>
			<xmin>64</xmin>
			<ymin>36</ymin>
			<xmax>127</xmax>
			<ymax>79</ymax>
		</bndbox>
	</object>
	<object>
		<name>nike</name>
		<pose>Unspecified</pose>
		<truncated>0</truncated>
		<difficult>0</difficult>
		<bndbox>
			<xmin>127</xmin>
			<ymin>93</ymin>
			<xmax>157</xmax>
			<ymax>110</ymax>
		</bndbox>
	</object>
	<object>
		<name>nike</name>
		<pose>Unspecified</pose>
		<truncated>0</truncated>
		<difficult>0</difficult>
		<bndbox>
			<xmin>181</xmin>
			<ymin>35</ymin>
			<xmax>225</xmax>
			<ymax>138</ymax>
		</bndbox>
	</object>
</annotation>
